{
  "lib": "Directory",
  "stunir_build_helpers": "Directory",
  "align_rust_haskell.sh": "File",
  "bootstrap.sh": "File",
  "build.sh": "File",
  "build_artifacts.sh": "File",
  "build_compiled.sh": "File",
  "build_docker.sh": "File",
  "build_haskell_first.sh": "File",
  "build_haskell_pipeline.sh": "File",
  "build_hosted.sh": "File",
  "build_native.sh": "File",
  "build_pipeline.sh": "File",
  "build_rust_pipeline.sh": "File",
  "build_targets.ps1": "File",
  "canonicalize.sh": "File",
  "clean.sh": "File",
  "compile.sh": "File",
  "discover_toolchain.ps1": "File",
  "discover_toolchain.sh": "File",
  "dispatch.sh": "File",
  "emit_shell.sh": "File",
  "ensure_deps.sh": "File",
  "full_pipeline_v1.sh": "File",
  "haskell_pipeline_complete.sh": "File",
  "master_dispatch.sh": "File",
  "master_dispatch_v1.sh": "File",
  "pipeline_haskell.sh": "File",
  "pipeline_python.sh": "File",
  "pipeline_rust.sh": "File",
  "probe_deps.sh": "File",
  "profile3_lib.sh": "File",
  "reset_ai_bins.sh": "File",
  "run_all_pipelines.sh": "File",
  "run_all_tests.sh": "File",
  "rust_pipeline_complete.sh": "File",
  "snapshot_receipts.sh": "File",
  "stunir_process.ps1": "File",
  "stunir_production.sh": "File",
  "stunir_spawn.ps1": "File",
  "test_confluence.sh": "File",
  "test_conformance.sh": "File",
  "test_full_pipeline.sh": "File",
  "test_haskell_pipeline.sh": "File",
  "test_haskell_rust_confluence.sh": "File",
  "test_interop.sh": "File",
  "test_pipeline_fixed.sh": "File",
  "test_provenance.sh": "File",
  "test_python_conformance.sh": "File",
  "test_rust_pipeline.sh": "File",
  "verify.sh": "File",
  "verify_conformance.sh": "File",
  "verify_deps.sh": "File",
  "verify_manifest.sh": "File",
  "verify_minimal.cmd": "File",
  "verify_minimal.ps1": "File",
  "verify_minimal.sh": "File",
  "verify_pipeline.sh": "File",
  "verify_profile3.sh": "File",
  "verify_shell.sh": "File",
  "verify_vectors.sh": "File"
}